quasar/__init__.py
quasar/__main__.py
quasar/launcher/__init__.py
quasar/launcher/splash.py
quasar/launcher/update_check.py
quasar/launcher/icons/quasar.svg
quasar/launcher/icons/splash.png
quasar/tests/__init__.py
quasar/tests/test_update_check.py
quasar/tutorials/__init__.py
quasar-1.13.0.dist-info/licenses/LICENSE
quasar-1.13.0.dist-info/METADATA
quasar-1.13.0.dist-info/WHEEL
quasar-1.13.0.dist-info/entry_points.txt
quasar-1.13.0.dist-info/top_level.txt
quasar-1.13.0.dist-info/RECORD
