Metadata-Version: 2.4
Name: Quasar
Version: 1.13.0
Summary: Quasar is a collection of data analysis toolboxes extending the Orange suite.
Home-page: https://quasar.codes
Author: Canadian Light Source, Biolab UL, Soleil, Elettra
Author-email: marko@toplak.io
License: GPLv3+
Keywords: orange3,spectroscopy,infrared
License-File: LICENSE
Requires-Dist: Orange3>=3.40.0
Requires-Dist: orange-spectroscopy>=0.9.0
Requires-Dist: orange-snom>=0.1.0
Dynamic: author
Dynamic: author-email
Dynamic: description
Dynamic: home-page
Dynamic: keywords
Dynamic: license
Dynamic: license-file
Dynamic: requires-dist
Dynamic: summary
